boolxai/__init__.py
boolxai/_version.py
boolxai/boolxai.py
boolxai/moves.py
boolxai/util.py
boolxai/classifiers/__init__.py
boolxai/classifiers/baseline_classifier.py
boolxai/classifiers/postprocessing.py
boolxai/classifiers/rule_classifier.py
boolxai/classifiers/util.py
boolxai/rules/__init__.py
boolxai/rules/literal.py
boolxai/rules/operators.py
boolxai/rules/rule.py
boolxai/rules/trivials.py
notebooks/__init__.py
notebooks/util.py
boolxai-1.0.0.dist-info/LICENSE
boolxai-1.0.0.dist-info/METADATA
boolxai-1.0.0.dist-info/NOTICES
boolxai-1.0.0.dist-info/WHEEL
boolxai-1.0.0.dist-info/top_level.txt
boolxai-1.0.0.dist-info/RECORD
