Metadata-Version: 2.1
Name: boolxai
Version: 1.0.0
Summary: BoolXAI: Explainable AI using expressive Boolean formulas
Home-page: https://github.com/fidelity/boolxai
Author: Collaboration between Fidelity Labs and AWS Quantum Solutions Lab
Project-URL: Source, https://github.com/fidelity/boolxai
Project-URL: Documentation, https://fidelity.github.io/boolxai/
Classifier: License :: OSI Approved :: Apache Software License
Classifier: Programming Language :: Python :: 3.8
Classifier: Operating System :: OS Independent
Requires-Python: >=3.8
License-File: LICENSE
License-File: NOTICES
Requires-Dist: numpy (==1.24.3)
Requires-Dist: scikit-learn (==1.2.2)
Provides-Extra: plot
Requires-Dist: ipython (==8.12.2) ; extra == 'plot'
Requires-Dist: networkx (==3.1) ; extra == 'plot'
Requires-Dist: pygraphviz (==1.11) ; extra == 'plot'
